filemanipulator/Examples.py
filemanipulator/__init__.py
filemanipulator/filemanipulator.py
filemanipulator-0.0.4.dist-info/LICENSE
filemanipulator-0.0.4.dist-info/METADATA
filemanipulator-0.0.4.dist-info/WHEEL
filemanipulator-0.0.4.dist-info/top_level.txt
filemanipulator-0.0.4.dist-info/RECORD
