Metadata-Version: 2.1
Name: filemanipulator
Version: 0.0.4
Summary: A module allowing for simple file manipulation tools, with the option to parse more sophisticated arguments for complex programming that would otherwise require many lines.
Home-page: https://github.com/Daniel-CG-Wright/filemanipulator
Author: Daniel Wright
Author-email: danielcgwright2@gmail.com
License: UNKNOWN
Project-URL: Documentation, https://github.com/Daniel-CG-Wright/filemanipulator
Platform: UNKNOWN
Classifier: Programming Language :: Python :: 3
Classifier: License :: OSI Approved :: MIT License
Classifier: Operating System :: OS Independent
Requires-Python: >=3.6
License-File: LICENSE
Requires-Dist: docutils
Requires-Dist: update-check
